lempel_ziv_complexity/__init__.py
lempel_ziv_complexity/lempel_ziv_complexity.py
lempel_ziv_complexity-0.2.2.dist-info/METADATA
lempel_ziv_complexity-0.2.2.dist-info/WHEEL
lempel_ziv_complexity-0.2.2.dist-info/top_level.txt
lempel_ziv_complexity-0.2.2.dist-info/RECORD
