Metadata-Version: 2.1
Name: lempel-ziv-complexity
Version: 0.2.2
Summary: Fast implementation of the Lempel-Ziv complexity function
Home-page: https://github.com/Naereen/Lempel-Ziv_Complexity
Author: Lilian Besson (Naereen)
Author-email: naereen@crans.org
License: OSI Approved :: MIT License
Project-URL: Bug Reports, https://github.com/Naereen/Lempel-Ziv_Complexity/issues
Project-URL: Source, https://github.com/Naereen/Lempel-Ziv_Complexity/tree/master/
Project-URL: Documentation, https://smpybandits.github.io/
Platform: UNKNOWN
Classifier: Intended Audience :: Science/Research
Classifier: License :: OSI Approved :: MIT License
Classifier: Programming Language :: Python :: 2
Classifier: Programming Language :: Python :: 3
Classifier: Programming Language :: Python :: Implementation :: CPython
Classifier: Topic :: Scientific/Engineering :: Information Analysis 
Classifier: Topic :: Scientific/Engineering :: Mathematics
Classifier: Development Status :: 4 - Beta
Classifier: Natural Language :: English
